Randomkey/__init__.py
Randomkey/key.py
Randomkey-0.0.5.dist-info/LICENSE.txt
Randomkey-0.0.5.dist-info/METADATA
Randomkey-0.0.5.dist-info/WHEEL
Randomkey-0.0.5.dist-info/top_level.txt
Randomkey-0.0.5.dist-info/RECORD
