Metadata-Version: 2.1
Name: Randomkey
Version: 0.0.5
Summary: 一个基于random模块，快速生成密码的模块|A module based on random module to quickly generate passwords
Home-page: https://codechina.csdn.net/qq_53280175/randomkey
Author: PYmili
Author-email: mc2005wj@163.com
Maintainer: PYmili
Maintainer-email: mc2005wj@163.com
License: MIT License
Platform: UNKNOWN
Classifier: Operating System :: OS Independent
Classifier: Natural Language :: Chinese (Simplified)
Classifier: Natural Language :: English
Classifier: License :: OSI Approved :: MIT License
Classifier: Programming Language :: Python :: 3.6
Classifier: Programming Language :: Python :: 3.7
Classifier: Programming Language :: Python :: 3.8
Classifier: Programming Language :: Python :: 3.9
Classifier: Topic :: Software Development :: Libraries
Requires-Python: >=3.7
License-File: LICENSE.txt
